ytdl_sub/__init__.py
ytdl_sub/main.py
ytdl_sub/cli/__init__.py
ytdl_sub/cli/entrypoint.py
ytdl_sub/cli/output_summary.py
ytdl_sub/cli/output_transaction_log.py
ytdl_sub/cli/parsers/__init__.py
ytdl_sub/cli/parsers/cli_to_sub.py
ytdl_sub/cli/parsers/dl.py
ytdl_sub/cli/parsers/main.py
ytdl_sub/config/__init__.py
ytdl_sub/config/config_file.py
ytdl_sub/config/config_validator.py
ytdl_sub/config/defaults.py
ytdl_sub/config/overrides.py
ytdl_sub/config/preset.py
ytdl_sub/config/preset_options.py
ytdl_sub/config/plugin/__init__.py
ytdl_sub/config/plugin/plugin.py
ytdl_sub/config/plugin/plugin_mapping.py
ytdl_sub/config/plugin/plugin_operation.py
ytdl_sub/config/plugin/preset_plugins.py
ytdl_sub/config/validators/__init__.py
ytdl_sub/config/validators/options.py
ytdl_sub/config/validators/variable_validation.py
ytdl_sub/downloaders/__init__.py
ytdl_sub/downloaders/source_plugin.py
ytdl_sub/downloaders/ytdl_options_builder.py
ytdl_sub/downloaders/ytdlp.py
ytdl_sub/downloaders/info_json/__init__.py
ytdl_sub/downloaders/info_json/info_json_downloader.py
ytdl_sub/downloaders/url/__init__.py
ytdl_sub/downloaders/url/downloader.py
ytdl_sub/downloaders/url/validators.py
ytdl_sub/entries/__init__.py
ytdl_sub/entries/base_entry.py
ytdl_sub/entries/entry.py
ytdl_sub/entries/entry_parent.py
ytdl_sub/entries/script/__init__.py
ytdl_sub/entries/script/custom_functions.py
ytdl_sub/entries/script/function_scripts.py
ytdl_sub/entries/script/variable_definitions.py
ytdl_sub/entries/script/variable_types.py
ytdl_sub/entries/variables/__init__.py
ytdl_sub/entries/variables/override_variables.py
ytdl_sub/plugins/__init__.py
ytdl_sub/plugins/audio_extract.py
ytdl_sub/plugins/chapters.py
ytdl_sub/plugins/date_range.py
ytdl_sub/plugins/embed_thumbnail.py
ytdl_sub/plugins/file_convert.py
ytdl_sub/plugins/filter_exclude.py
ytdl_sub/plugins/filter_include.py
ytdl_sub/plugins/format.py
ytdl_sub/plugins/match_filters.py
ytdl_sub/plugins/music_tags.py
ytdl_sub/plugins/nfo_tags.py
ytdl_sub-2026.1.30.dist-info/licenses/LICENSE
ytdl_sub-2026.1.30.dist-info/METADATA
ytdl_sub-2026.1.30.dist-info/WHEEL
ytdl_sub-2026.1.30.dist-info/entry_points.txt
ytdl_sub-2026.1.30.dist-info/top_level.txt
ytdl_sub-2026.1.30.dist-info/RECORD
