Metadata-Version: 2.4
Name: ytdl-sub
Version: 2026.1.30
Summary: Automate downloading metadata generation with YoutubeDL
Author: Jesse Bannon
License:                     GNU GENERAL PUBLIC LICENSE
Project-URL: Homepage, https://github.com/jmbannon/ytdl-sub
Platform: Unix
Classifier: Topic :: Multimedia :: Sound/Audio
Classifier: Topic :: Multimedia :: Video
Classifier: License :: Public Domain
Classifier: Environment :: Console
Classifier: Programming Language :: Python :: 3.10
Classifier: Programming Language :: Python :: 3.11
Requires-Python: >=3.10
License-File: LICENSE
Requires-Dist: yt-dlp[default]==2026.1.29
Requires-Dist: colorama~=0.4
Requires-Dist: mergedeep~=1.3
Requires-Dist: mediafile~=0.12
Requires-Dist: PyYAML~=6.0
Provides-Extra: test
Requires-Dist: coverage[toml]<8.0,>=6.3; extra == "test"
Requires-Dist: pytest<9.0,>=7.2; extra == "test"
Requires-Dist: pytest-rerunfailures<17,>=14; extra == "test"
Provides-Extra: lint
Requires-Dist: black==24.10.0; extra == "lint"
Requires-Dist: isort==7.0.0; extra == "lint"
Requires-Dist: pylint==4.0.1; extra == "lint"
Provides-Extra: docs
Requires-Dist: sphinx<10,>=7; extra == "docs"
Requires-Dist: sphinx-rtd-theme<4,>=2; extra == "docs"
Requires-Dist: sphinx-book-theme~=1.0; extra == "docs"
Requires-Dist: sphinx-copybutton~=0.5; extra == "docs"
Requires-Dist: sphinx_design~=0.6; extra == "docs"
Provides-Extra: build
Requires-Dist: build~=1.2; extra == "build"
Requires-Dist: twine<7,>=5; extra == "build"
Requires-Dist: pyinstaller~=6.5; extra == "build"
Dynamic: license-file
